{
 "fromRepo": ".",
 "fromCommit": "0000000000000000000000000000000000000000",
 "toRef": "refs/heads/master",
 
 "ignoreCommitsIfMessageMatches": "^\\[maven-release-plugin\\].*|^\\[Gradle Release Plugin\\].*|^Merge.*",
 "readableTagName": "/([^/]+?)$",
 "dateFormat": "YYYY-MM-dd HH:mm:ss",
 "untaggedName": "No tag",
 "noIssueName": "No issue",
 "templatePath": "git-changelog-template.mustache",
 "timeZone": "UTC",
 "removeIssueFromMessage": "true",
 
 "jiraServer": "",
 "jiraIssuePattern": "\\b[a-zA-Z]([a-zA-Z]+)-([0-9]+)\\b",

 "customIssues": [
  {"name": "Github", "pattern": "#[0-9]+", "link": "" } 
 ]
}
